main.py
git_python-1.0.3.dist-info/METADATA
git_python-1.0.3.dist-info/WHEEL
git_python-1.0.3.dist-info/entry_points.txt
git_python-1.0.3.dist-info/top_level.txt
git_python-1.0.3.dist-info/RECORD
